{"is_source_file": true, "format": "JavaScript", "description": "This file defines functions for interacting with the CoinGecko public cryptocurrency API, specifically fetching and processing top market data.", "external_files": ["../../httpClient", "../util/retry", "../util/sanitization"], "external_methods": ["httpFetch", "withRetry", "cleanObject"], "published": ["getTopMarkets"], "classes": [], "methods": [{"name": "getTopMarkets()", "description": "Fetches top cryptocurrency markets from CoinGecko, processes and returns the data.", "scope": "", "scopeKind": ""}], "calls": ["httpFetch", "withRetry", "cleanObject"], "search-terms": ["cryptoApi", "CoinGecko", "getTopMarkets", "public API", "cryptocurrency", "market data"], "state": 2, "file_id": 35, "knowledge_revision": 74, "git_revision": "", "ctags": [{"_type": "tag", "name": "getTopMarkets", "path": "/home/kavia/workspace/code-generation/open-api-data-dashboard-225692-225701/react_frontend/src/services/apis/public/cryptoApi.js", "pattern": "/^export async function getTopMarkets() {$/", "language": "JavaScript", "kind": "function", "signature": "()"}], "hash": "2c6f372775f0f4c81d37cca309e1a094", "format-version": 4, "code-base-name": "react_frontend", "filename": "react_frontend/src/services/apis/public/cryptoApi.js", "revision_history": [{"74": ""}]}